[{"name" : "Martin Dubravka", "stat" : "6.7"}, {"name" : "Federico Fernández", "stat" : "7.2"}, {"name" : "Ciaran Clark", "stat" : "6.4"}, {"name" : "Paul Dummett", "stat" : "6.3"}, {"name" : "Javier Manquillo", "stat" : "6.4"}, {"name" : "Jonjo Shelvey", "stat" : "7.7"}, {"name" : "Isaac Hayden", "stat" : "6.6"}, {"name" : "Jetro Willems", "stat" : "7.3"}, {"name" : "Miguel Almiron", "stat" : "7.8"}, {"name" : "Joelinton", "stat" : "7.0"}, {"name" : "Allan Saint-Maximin", "stat" : "7.0"}, {"name" : "Raheem Sterling", "stat" : "7.0"}, {"name" : "Gabriel Jesus", "stat" : "6.8"}, {"name" : "Riyad Mahrez", "stat" : "7.1"}, {"name" : "David Silva", "stat" : "7.5"}, {"name" : "Ilkay Gündogan", "stat" : "7.2"}, {"name" : "Kevin De Bruyne", "stat" : "8.8"}, {"name" : "Benjamin Mendy", "stat" : "6.0"}, {"name" : "Fernandinho", "stat" : "6.8"}, {"name" : "John Stones", "stat" : "6.8"}, {"name" : "Kyle Walker", "stat" : "6.5"}, {"name" : "Ederson Moraes", "stat" : "5.6"}, {"name" : "Steve Bruce", "stat" : ""}, {"name" : "Josep Guardiola", "stat" : ""}, {"name" : "Karl Darlow", "stat" : ""}, {"name" : "Emil Krafth", "stat" : ""}, {"name" : "Fabian Schär", "stat" : ""}, {"name" : "Christian Atsu", "stat" : "6.5"}, {"name" : "Matthew Longstaff", "stat" : ""}, {"name" : "Sean Longstaff", "stat" : ""}, {"name" : "Dwight Gayle", "stat" : "5.6"}, {"name" : "Claudio Bravo", "stat" : ""}, {"name" : "Angelino", "stat" : ""}, {"name" : "Joao Cancelo", "stat" : ""}, {"name" : "Nicolas Otamendi", "stat" : ""}, {"name" : "Bernardo Silva", "stat" : "5.8"}, {"name" : "Phil Foden", "stat" : "6.0"}, {"name" : "Rodri", "stat" : ""}, {"name" : "Nick Pope", "stat" : "4.9"}, {"name" : "Phil Bardsley", "stat" : "6.7"}, {"name" : "James Tarkowski", "stat" : "6.4"}, {"name" : "Ben Mee", "stat" : "5.6"}, {"name" : "Charlie Taylor", "stat" : "6.0"}, {"name" : "Robert Brady", "stat" : "6.4"}, {"name" : "Jack Cork", "stat" : "6.3"}, {"name" : "Jeff Hendrick", "stat" : "6.3"}, {"name" : "Dwight McNeil", "stat" : "6.9"}, {"name" : "Chris Wood", "stat" : "5.8"}, {"name" : "Ashley Barnes", "stat" : "5.4"}, {"name" : "Jordan Ayew", "stat" : "6.2"}, {"name" : "Wilfried Zaha", "stat" : "8.2"}, {"name" : "Andros Townsend", "stat" : "6.6"}, {"name" : "James McArthur", "stat" : "6.5"}, {"name" : "Luka Milivojevic", "stat" : "6.1"}, {"name" : "Cheikhou Kouyaté", "stat" : "6.1"}, {"name" : "Patrick van Aanholt", "stat" : "6.9"}, {"name" : "Scott Dann", "stat" : "7.3"}, {"name" : "James Tomkins", "stat" : "7.4"}, {"name" : "Martin Kelly", "stat" : "6.8"}, {"name" : "Vicente Guaita", "stat" : "7.7"}, {"name" : "Sean Dyche", "stat" : ""}, {"name" : "Roy Hodgson", "stat" : ""}, {"name" : "Joe Hart", "stat" : ""}, {"name" : "Ben Gibson", "stat" : ""}, {"name" : "Erik Pieters", "stat" : "6.0"}, {"name" : "Matthew Lowton", "stat" : ""}, {"name" : "Aaron Lennon", "stat" : "6.1"}, {"name" : "Danny Drinkwater", "stat" : ""}, {"name" : "Jay Rodriguez", "stat" : "6.0"}, {"name" : "Wayne Hennessey", "stat" : ""}, {"name" : "Jairo Riedewald", "stat" : ""}, {"name" : "Jeffrey Schlupp", "stat" : "7.1"}, {"name" : "Mamadou Sakho", "stat" : "6.4"}, {"name" : "James McCarthy", "stat" : ""}, {"name" : "Victor Camarasa", "stat" : ""}, {"name" : "Christian Benteke", "stat" : ""}, {"name" : "Kepa Arrizabalaga", "stat" : "6.5"}, {"name" : "Reece James", "stat" : "7.7"}, {"name" : "Kurt Zouma", "stat" : "7.2"}, {"name" : "Fikayo Tomori", "stat" : "6.4"}, {"name" : "Emerson", "stat" : "7.3"}, {"name" : "Jorginho", "stat" : "5.6"}, {"name" : "Mateo Kovacic", "stat" : "6.9"}, {"name" : "Pedro Rodriguez", "stat" : "6.3"}, {"name" : "Mason Mount", "stat" : "6.5"}, {"name" : "Christian Pulisic", "stat" : "6.3"}, {"name" : "Olivier Giroud", "stat" : "6.2"}, {"name" : "Michail Antonio", "stat" : "6.9"}, {"name" : "Felipe Anderson", "stat" : "7.3"}, {"name" : "Pablo Fornals", "stat" : "7.1"}, {"name" : "Mark Noble", "stat" : "6.4"}, {"name" : "Declan Rice", "stat" : "7.4"}, {"name" : "Robert Snodgrass", "stat" : "7.1"}, {"name" : "Aaron Cresswell", "stat" : "7.8"}, {"name" : "Angelo Ogbonna", "stat" : "7.3"}, {"name" : "Fabian Balbuena", "stat" : "7.5"}, {"name" : "Ryan Fredericks", "stat" : "7.3"}, {"name" : "David Martin", "stat" : "8.1"}, {"name" : "Frank Lampard", "stat" : ""}, {"name" : "Manuel Pellegrini", "stat" : ""}, {"name" : "Wilfredo Caballero", "stat" : ""}, {"name" : "Andreas Christensen", "stat" : ""}, {"name" : "César Azpilicueta", "stat" : ""}, {"name" : "N'Golo Kanté", "stat" : "6.0"}, {"name" : "Callum Hudson-Odoi", "stat" : "6.6"}, {"name" : "Michy Batshuayi", "stat" : ""}, {"name" : "Willian", "stat" : "6.3"}, {"name" : "Roberto", "stat" : ""}, {"name" : "Arthur Masuaku", "stat" : ""}, {"name" : "Pablo Zabaleta", "stat" : ""}, {"name" : "Carlos Sánchez", "stat" : ""}, {"name" : "Albian Ajeti", "stat" : ""}, {"name" : "Andriy Yarmolenko", "stat" : "5.9"}, {"name" : "Sebastien Haller", "stat" : "6.2"}, {"name" : "Alisson Becker", "stat" : "6.5"}, {"name" : "Trent Alexander-Arnold", "stat" : "8.6"}, {"name" : "Dejan Lovren", "stat" : "6.8"}, {"name" : "Virgil van Dijk", "stat" : "9.0"}, {"name" : "Andrew Robertson", "stat" : "6.8"}, {"name" : "Alex Oxlade-Chamberlain", "stat" : "7.3"}, {"name" : "Jordan Henderson", "stat" : "6.9"}, {"name" : "Georginio Wijnaldum", "stat" : "6.9"}, {"name" : "Mohamed Salah", "stat" : "6.7"}, {"name" : "Roberto Firmino", "stat" : "6.1"}, {"name" : "Sadio Mané", "stat" : "7.9"}, {"name" : "Yves Bissouma", "stat" : "6.2"}, {"name" : "Aaron Connolly", "stat" : "5.8"}, {"name" : "Pascal Gross", "stat" : "6.5"}, {"name" : "Aaron Mooy", "stat" : "6.5"}, {"name" : "Dale Stephens", "stat" : "6.3"}, {"name" : "Davy Pröpper", "stat" : "7.2"}, {"name" : "Daniel Burn", "stat" : "7.2"}, {"name" : "Lewis Dunk", "stat" : "7.6"}, {"name" : "Adam Webster", "stat" : "6.8"}, {"name" : "Martin Montoya", "stat" : "6.5"}, {"name" : "Mathew Ryan", "stat" : "6.6"}, {"name" : "Jürgen Klopp", "stat" : ""}, {"name" : "Graham Potter", "stat" : ""}, {"name" : "Adrian", "stat" : "5.0"}, {"name" : "Joseph Gomez", "stat" : ""}, {"name" : "Adam Lallana", "stat" : "6.0"}, {"name" : "James Milner", "stat" : ""}, {"name" : "Naby Keita", "stat" : ""}, {"name" : "Divock Origi", "stat" : ""}, {"name" : "Xherdan Shaqiri", "stat" : ""}, {"name" : "David Button", "stat" : ""}, {"name" : "Shane Duffy", "stat" : ""}, {"name" : "Ezequiel Schelotto", "stat" : ""}, {"name" : "Steven Alzate", "stat" : "5.9"}, {"name" : "Glenn Murray", "stat" : ""}, {"name" : "Leandro Trossard", "stat" : "5.5"}, {"name" : "Neal Maupay", "stat" : "5.6"}, {"name" : "Paulo Gazzaniga", "stat" : "7.7"}, {"name" : "Serge Aurier", "stat" : "7.3"}, {"name" : "Davinson Sánchez", "stat" : "6.5"}, {"name" : "Toby Alderweireld", "stat" : "7.5"}, {"name" : "Jan Vertonghen", "stat" : "6.7"}, {"name" : "Eric Dier", "stat" : "6.8"}, {"name" : "Tanguy Ndombélé", "stat" : "7.8"}, {"name" : "Moussa Sissoko", "stat" : "8.3"}, {"name" : "Dele Alli", "stat" : "9.3"}, {"name" : "Heung-Min Son", "stat" : "8.6"}, {"name" : "Harry Kane", "stat" : "7.0"}, {"name" : "Callum Wilson", "stat" : "5.5"}, {"name" : "Dominic Solanke", "stat" : "6.5"}, {"name" : "Arnaut Danjuma", "stat" : "6.7"}, {"name" : "Lewis Cook", "stat" : "6.3"}, {"name" : "Jefferson Lerma", "stat" : "6.6"}, {"name" : "Ryan Fraser", "stat" : "6.0"}, {"name" : "Diego Rico", "stat" : "5.9"}, {"name" : "Nathan Aké", "stat" : "5.6"}, {"name" : "Steve Cook", "stat" : "6.0"}, {"name" : "Jack Stacey", "stat" : "5.9"}, {"name" : "Aaron Ramsdale", "stat" : "4.9"}, {"name" : "José Mourinho", "stat" : ""}, {"name" : "Eddie Howe", "stat" : ""}, {"name" : "Alfie Whiteman", "stat" : ""}, {"name" : "Danny Rose", "stat" : ""}, {"name" : "Kyle Walker-Peters", "stat" : ""}, {"name" : "Christian Eriksen", "stat" : ""}, {"name" : "Giovani Lo Celso", "stat" : ""}, {"name" : "Harry Winks", "stat" : ""}, {"name" : "Lucas Moura", "stat" : "6.4"}, {"name" : "Artur Boruc", "stat" : ""}, {"name" : "Chris Mepham", "stat" : ""}, {"name" : "Jack Simpson", "stat" : ""}, {"name" : "Dan Gosling", "stat" : "5.4"}, {"name" : "Gavin Kilkenny", "stat" : ""}, {"name" : "Harry Wilson", "stat" : "8.0"}, {"name" : "Christian Saydee", "stat" : ""}, {"name" : "Alex McCarthy", "stat" : "6.9"}, {"name" : "Cédric Soares", "stat" : "6.8"}, {"name" : "Jack Stephens", "stat" : "6.2"}, {"name" : "Jan Bednarek", "stat" : "7.0"}, {"name" : "Ryan Bertrand", "stat" : "6.7"}, {"name" : "Moussa Djenepo", "stat" : "8.3"}, {"name" : "James Ward-Prowse", "stat" : "7.6"}, {"name" : "Pierre-Emile Højbjerg", "stat" : "7.9"}, {"name" : "Nathan Redmond", "stat" : "6.1"}, {"name" : "Danny Ings", "stat" : "8.1"}, {"name" : "Michael Obafemi", "stat" : "6.3"}, {"name" : "Ismaila Sarr", "stat" : "7.6"}, {"name" : "Gerard Deulofeu", "stat" : "5.6"}, {"name" : "Will Hughes", "stat" : "5.9"}, {"name" : "Jose Holebas", "stat" : "5.5"}, {"name" : "Abdoulaye Doucouré", "stat" : "6.5"}, {"name" : "Étienne Capoue", "stat" : "7.0"}, {"name" : "Kiko", "stat" : "6.7"}, {"name" : "Adam Masina", "stat" : "6.1"}, {"name" : "Craig Cathcart", "stat" : "6.0"}, {"name" : "Adrian Mariappa", "stat" : "6.3"}, {"name" : "Ben Foster", "stat" : "6.2"}, {"name" : "Ralph Hasenhüttl", "stat" : ""}, {"name" : "Quique Sanchez Flores", "stat" : ""}, {"name" : "Angus Gunn", "stat" : ""}, {"name" : "Maya Yoshida", "stat" : ""}, {"name" : "Yan Valery", "stat" : "6.4"}, {"name" : "Oriol Romeu", "stat" : ""}, {"name" : "Sofiane Boufal", "stat" : "6.9"}, {"name" : "Che Adams", "stat" : ""}, {"name" : "Shane Long", "stat" : "5.6"}, {"name" : "Heurelho Gomes", "stat" : ""}, {"name" : "Dimitri Foulquier", "stat" : ""}, {"name" : "Nathaniel Chalobah", "stat" : "5.5"}, {"name" : "Quina", "stat" : ""}, {"name" : "Roberto Pereyra", "stat" : ""}, {"name" : "Andre Gray", "stat" : "5.5"}, {"name" : "Troy Deeney", "stat" : ""}, {"name" : "Tim Krul", "stat" : "6.3"}, {"name" : "Max Aarons", "stat" : "6.0"}, {"name" : "Christoph Zimmermann", "stat" : "6.9"}, {"name" : "Ben Godfrey", "stat" : "6.4"}, {"name" : "Sam Byram", "stat" : "6.2"}, {"name" : "Ibrahim Amadou", "stat" : "6.7"}, {"name" : "Tom Trybull", "stat" : "6.6"}, {"name" : "Todd Cantwell", "stat" : "7.8"}, {"name" : "Kenny McLean", "stat" : "6.7"}, {"name" : "Onel Hernández", "stat" : "7.5"}, {"name" : "Teemu Pukki", "stat" : "7.8"}, {"name" : "Alexandre Lacazette", "stat" : "5.6"}, {"name" : "Mesut Özil", "stat" : "7.4"}, {"name" : "Joseph Willock", "stat" : "6.6"}, {"name" : "Pierre-Emerick Aubameyang", "stat" : "8.8"}, {"name" : "Matteo Guendouzi", "stat" : "6.4"}, {"name" : "Granit Xhaka", "stat" : "6.7"}, {"name" : "Sead Kolasinac", "stat" : "6.6"}, {"name" : "David Luiz", "stat" : "6.0"}, {"name" : "Shkodran Mustafi", "stat" : "6.6"}, {"name" : "Calum Chambers", "stat" : "6.7"}, {"name" : "Bernd Leno", "stat" : "7.5"}, {"name" : "Daniel Farke", "stat" : ""}, {"name" : "Fredrik Ljungberg", "stat" : ""}, {"name" : "Ralf Fährmann", "stat" : ""}, {"name" : "Jamal Lewis", "stat" : ""}, {"name" : "Dennis Srbeny", "stat" : ""}, {"name" : "Emiliano Buendia", "stat" : ""}, {"name" : "Marco Stiepermann", "stat" : ""}, {"name" : "Mario Vrancic", "stat" : ""}, {"name" : "Patrick Roberts", "stat" : ""}, {"name" : "Emiliano Martinez", "stat" : ""}, {"name" : "Kieran Tierney", "stat" : ""}, {"name" : "Sokratis Papastathopoulos", "stat" : ""}, {"name" : "Lucas Torreira", "stat" : "6.4"}, {"name" : "Bukayo Saka", "stat" : "5.8"}, {"name" : "Gabriel Martinelli", "stat" : ""}, {"name" : "Nicolas Pépé", "stat" : ""}, {"name" : "Rui Patricio", "stat" : "6.6"}, {"name" : "Leander Dendoncker", "stat" : "7.3"}, {"name" : "Conor Coady", "stat" : "6.5"}, {"name" : "Max Kilman", "stat" : "6.7"}, {"name" : "Matt Doherty", "stat" : "8.3"}, {"name" : "Joao Moutinho", "stat" : "6.8"}, {"name" : "Ruben Neves", "stat" : "6.5"}, {"name" : "Jonny", "stat" : "6.4"}, {"name" : "Adama Traoré", "stat" : "7.0"}, {"name" : "Raul Jiménez", "stat" : "7.8"}, {"name" : "Diogo Jota", "stat" : "5.9"}, {"name" : "Lys Mousset", "stat" : "6.6"}, {"name" : "David McGoldrick", "stat" : "6.5"}, {"name" : "Enda Stevens", "stat" : "6.5"}, {"name" : "John Fleck", "stat" : "6.7"}, {"name" : "Oliver Norwood", "stat" : "7.7"}, {"name" : "John Lundstram", "stat" : "6.8"}, {"name" : "George Baldock", "stat" : "7.2"}, {"name" : "Jack O'Connell", "stat" : "6.3"}, {"name" : "John Egan", "stat" : "6.4"}, {"name" : "Chris Basham", "stat" : "7.6"}, {"name" : "Dean Henderson", "stat" : "6.9"}, {"name" : "Nuno Espirito Santo", "stat" : ""}, {"name" : "Chris Wilder", "stat" : ""}, {"name" : "John Ruddy", "stat" : ""}, {"name" : "Jesus Vallejo", "stat" : ""}, {"name" : "Ruben Vinagre", "stat" : ""}, {"name" : "Luke Cundle", "stat" : ""}, {"name" : "Owen Otasowie", "stat" : ""}, {"name" : "Pedro Neto", "stat" : ""}, {"name" : "Patrick Cutrone", "stat" : ""}, {"name" : "Simon Moore", "stat" : ""}, {"name" : "Phil Jagielka", "stat" : ""}, {"name" : "Luke Freeman", "stat" : ""}, {"name" : "Muhamed Besic", "stat" : ""}, {"name" : "Billy Sharp", "stat" : ""}, {"name" : "Callum Robinson", "stat" : ""}, {"name" : "Oliver McBurnie", "stat" : "6.4"}, {"name" : "Kasper Schmeichel", "stat" : "6.5"}, {"name" : "Ricardo Pereira", "stat" : "8.1"}, {"name" : "Jonny Evans", "stat" : "7.3"}, {"name" : "Caglar Söyüncü", "stat" : "7.0"}, {"name" : "Ben Chilwell", "stat" : "7.5"}, {"name" : "Wilfred Ndidi", "stat" : "8.2"}, {"name" : "Ayoze Pérez", "stat" : "6.3"}, {"name" : "Youri Tielemans", "stat" : "6.9"}, {"name" : "James Maddison", "stat" : "7.3"}, {"name" : "Harvey Barnes", "stat" : "7.0"}, {"name" : "Jamie Vardy", "stat" : "7.8"}, {"name" : "Richarlison", "stat" : "7.7"}, {"name" : "Dominic Calvert-Lewin", "stat" : "5.4"}, {"name" : "Alex Iwobi", "stat" : "5.7"}, {"name" : "Lucas Digne", "stat" : "7.7"}, {"name" : "Gylfi Sigurdsson", "stat" : "6.4"}, {"name" : "Tom Davies", "stat" : "6.7"}, {"name" : "Djibril Sidibé", "stat" : "7.1"}, {"name" : "Michael Keane", "stat" : "6.2"}, {"name" : "Yerry Mina", "stat" : "6.6"}, {"name" : "Mason Holgate", "stat" : "6.3"}, {"name" : "Jordan Pickford", "stat" : "6.0"}, {"name" : "Brendan Rodgers", "stat" : ""}, {"name" : "Marco Silva", "stat" : ""}, {"name" : "Danny Ward", "stat" : ""}, {"name" : "James Justin", "stat" : ""}, {"name" : "Wes Morgan", "stat" : ""}, {"name" : "Dennis Praet", "stat" : ""}, {"name" : "Hamza Choudhury", "stat" : ""}, {"name" : "Kelechi Iheanacho", "stat" : "7.6"}, {"name" : "Marc Albrighton", "stat" : ""}, {"name" : "Jonas Lössl", "stat" : ""}, {"name" : "Leighton Baines", "stat" : ""}, {"name" : "Anthony Gordon", "stat" : ""}, {"name" : "Bernard", "stat" : ""}, {"name" : "Morgan Schneiderlin", "stat" : "6.0"}, {"name" : "Cenk Tosun", "stat" : ""}, {"name" : "Moise Kean", "stat" : "5.7"}, {"name" : "David De Gea", "stat" : "5.1"}, {"name" : "Aaron Wan-Bissaka", "stat" : "6.9"}, {"name" : "Victor Nilsson Lindelöf", "stat" : "7.4"}, {"name" : "Harry Maguire", "stat" : "6.2"}, {"name" : "Brandon Williams", "stat" : "6.1"}, {"name" : "Andreas Pereira", "stat" : "5.7"}, {"name" : "Fred", "stat" : "6.9"}, {"name" : "Daniel James", "stat" : "5.8"}, {"name" : "Juan Mata", "stat" : "6.3"}, {"name" : "Marcus Rashford", "stat" : "7.1"}, {"name" : "Anthony Martial", "stat" : "6.9"}, {"name" : "Jack Grealish", "stat" : "7.9"}, {"name" : "Wesley", "stat" : "6.3"}, {"name" : "Anwar El-Ghazi", "stat" : ""}, {"name" : "Conor Hourihane", "stat" : "6.8"}, {"name" : "Douglas Luiz", "stat" : "7.0"}, {"name" : "John McGinn", "stat" : "7.4"}, {"name" : "Matt Targett", "stat" : "7.8"}, {"name" : "Tyrone Mings", "stat" : "7.0"}, {"name" : "Ezri Konsa", "stat" : "6.0"}, {"name" : "Frédéric Guilbert", "stat" : "6.9"}, {"name" : "Tom Heaton", "stat" : "5.7"}, {"name" : "Ole Gunnar Solskjær", "stat" : ""}, {"name" : "Dean Smith", "stat" : ""}, {"name" : "Lee Grant", "stat" : ""}, {"name" : "Ashley Young", "stat" : ""}, {"name" : "Axel Tuanzebe", "stat" : ""}, {"name" : "James Garner", "stat" : ""}, {"name" : "Luke Shaw", "stat" : "5.9"}, {"name" : "Jesse Lingard", "stat" : "6.3"}, {"name" : "Mason Greenwood", "stat" : ""}, {"name" : "Ørjan Håskjold Nyland", "stat" : ""}, {"name" : "Ahmed El Mohamady", "stat" : ""}, {"name" : "Björn Engels", "stat" : ""}, {"name" : "Henri Lansbury", "stat" : ""}, {"name" : "Marvelous Nakamba", "stat" : ""}, {"name" : "Trezeguet", "stat" : "6.6"}, {"name" : "Jonathan Kodjia", "stat" : ""}]